original_metaplex_python/__init__.py
original_metaplex_python/__pkg__.py
original_metaplex_python/metaplex/__init__.py
original_metaplex_python/metaplex/metaplex.py
original_metaplex_python/metaplex/core_plugins/__init__.py
original_metaplex_python/metaplex/core_plugins/plugin.py
original_metaplex_python/metaplex/errors/__init__.py
original_metaplex_python/metaplex/errors/irys_error.py
original_metaplex_python/metaplex/errors/metaplex_error.py
original_metaplex_python/metaplex/errors/program_error.py
original_metaplex_python/metaplex/errors/read_api_error.py
original_metaplex_python/metaplex/errors/rpc_error.py
original_metaplex_python/metaplex/errors/sdk_error.py
original_metaplex_python/metaplex/identity_module/__init__.py
original_metaplex_python/metaplex/identity_module/identity_client.py
original_metaplex_python/metaplex/identity_module/identity_driver.py
original_metaplex_python/metaplex/identity_module/plugin.py
original_metaplex_python/metaplex/irys_storage/__init__.py
original_metaplex_python/metaplex/irys_storage/irys_storage_driver.py
original_metaplex_python/metaplex/irys_storage/plugin.py
original_metaplex_python/metaplex/keypair_identity/__init__.py
original_metaplex_python/metaplex/keypair_identity/keypair_identity_driver.py
original_metaplex_python/metaplex/keypair_identity/plugin.py
original_metaplex_python/metaplex/nft_module/__init__.py
original_metaplex_python/metaplex/nft_module/authorization.py
original_metaplex_python/metaplex/nft_module/delegate_input.py
original_metaplex_python/metaplex/nft_module/delegate_type.py
original_metaplex_python/metaplex/nft_module/errors.py
original_metaplex_python/metaplex/nft_module/nft_builders_client.py
original_metaplex_python/metaplex/nft_module/nft_client.py
original_metaplex_python/metaplex/nft_module/nft_pdas_client.py
original_metaplex_python/metaplex/nft_module/plugin.py
original_metaplex_python/metaplex/nft_module/models/__init__.py
original_metaplex_python/metaplex/nft_module/models/json_metadata.py
original_metaplex_python-0.0.1a2.dist-info/LICENSE
original_metaplex_python-0.0.1a2.dist-info/METADATA
original_metaplex_python-0.0.1a2.dist-info/WHEEL
original_metaplex_python-0.0.1a2.dist-info/top_level.txt
original_metaplex_python-0.0.1a2.dist-info/RECORD
