Metadata-Version: 2.1
Name: original-metaplex-python
Version: 0.0.1a2
Summary: Python port of Metaplex JS SDK - https://github.com/metaplex-foundation/js
Home-page: https://github.com/getoriginal/original-metaplex-python
Author: Original
Author-email: support@getoriginal.com
Requires-Python: >=3.7
License-File: LICENSE
Requires-Dist: aiohttp (<4.0,>=3.9.3)
Requires-Dist: aiosignal (<2.0,>=1.3.1)
Requires-Dist: anchorpy-core (<0.3.0,>=0.2.0)
Requires-Dist: anyio (<5.0,>=4.3.0)
Requires-Dist: async-timeout (<5.0,>=4.0.3)
Requires-Dist: attrs (<24.0,>=23.2.0)
Requires-Dist: solana (<0.33.0,>=0.32.0)
Requires-Dist: anchorpy (<0.20.0,>=0.19.1)
Requires-Dist: construct (<3.0,>=2.10.68)
Requires-Dist: borsh-construct (<0.2.0,>=0.1.0)
Requires-Dist: construct-typing (<0.6.0,>=0.5.6)
Requires-Dist: ed25519 (<2.0,>=1.5)
Requires-Dist: jsonrpcclient (<5.0,>=4.0.3)
Requires-Dist: pynacl (<2.0,>=1.5.0)
Requires-Dist: requests (<3.0,>=2.31.0)
Requires-Dist: types-requests (<3.0,>=2.31.0.20240218)
Provides-Extra: ci
Requires-Dist: black ; extra == 'ci'
Requires-Dist: flake8 ; extra == 'ci'
Requires-Dist: flake8-isort ; extra == 'ci'
Requires-Dist: flake8-bugbear ; extra == 'ci'
Requires-Dist: pytest-cov ; extra == 'ci'
Requires-Dist: mypy ; extra == 'ci'
Requires-Dist: types-requests ; extra == 'ci'
Provides-Extra: test
Requires-Dist: pytest ; extra == 'test'
Requires-Dist: pytest-asyncio (<=0.21.1) ; extra == 'test'
Requires-Dist: python-dotenv ; extra == 'test'
